proper_forms/__init__.py
proper_forms/fields/__init__.py
proper_forms/fields/boolean.py
proper_forms/fields/date.py
proper_forms/fields/date_time.py
proper_forms/fields/email.py
proper_forms/fields/field.py
proper_forms/fields/file.py
proper_forms/fields/float.py
proper_forms/fields/hex_color.py
proper_forms/fields/integer.py
proper_forms/fields/month.py
proper_forms/fields/password.py
proper_forms/fields/slug.py
proper_forms/fields/splitted.py
proper_forms/fields/splitted_date_time.py
proper_forms/fields/text.py
proper_forms/fields/time.py
proper_forms/fields/url.py
proper_forms/form.py
proper_forms/ftypes/__init__.py
proper_forms/ftypes/boolean.py
proper_forms/ftypes/color.py
proper_forms/ftypes/date.py
proper_forms/ftypes/email.py
proper_forms/ftypes/slug.py
proper_forms/ftypes/time.py
proper_forms/ftypes/url.py
proper_forms/utils.py
proper_forms/validators.py
proper_forms-0.8.dist-info/METADATA
proper_forms-0.8.dist-info/WHEEL
proper_forms-0.8.dist-info/RECORD
