Metadata-Version: 2.1
Name: proper_forms
Version: 0.8
Summary: A proper flexible Python form library
Home-page: https://proper-forms.scaletti.dev/
License: MIT
Author: Juan-Pablo Scaletti
Author-email: juanpablo@jpscaletti.com
Requires-Python: >=3.9,<4.0
Classifier: Development Status :: 4 - Beta
Classifier: Environment :: Web Environment
Classifier: Intended Audience :: Developers
Classifier: License :: OSI Approved :: MIT License
Classifier: Programming Language :: Python :: 3
Classifier: Programming Language :: Python :: 3.9
Classifier: Programming Language :: Python :: 3.10
Classifier: Programming Language :: Python :: 3.11
Classifier: Programming Language :: Python :: 3.12
Classifier: Programming Language :: Python :: 3 :: Only
Classifier: Topic :: Internet :: WWW/HTTP :: Dynamic Content
Classifier: Topic :: Software Development :: Libraries
Classifier: Topic :: Software Development :: Libraries :: Python Modules
Classifier: Topic :: Software Development :: User Interfaces
Classifier: Topic :: Text Processing :: Markup :: HTML
Classifier: Typing :: Typed
Requires-Dist: dnspython (>=1.15)
Requires-Dist: email-validator (>=1.1)
Requires-Dist: idna (>=2.8)
Requires-Dist: markupsafe (>=1.1)
Requires-Dist: python-slugify (>=3.0)
Project-URL: Repository, https://github.com/jpsca/proper-forms
